{
  "admin": [],
  "owner": [
    {
      "userName": "poonam",
      "email": "poonam@gmail.com",
      "panNumber": "gthff4444p",
      "mobileNumber": "98989898",
      "gender": "female",
      "password": "poonam$34",
      "id": 1
    },
    {
      "userName": "Pooja",
      "email": "pooja@gmail.com",
      "panNumber": "gthff4444p",
      "mobileNumber": "98989898",
      "gender": "female",
      "password": "pooja$34",
      "id": 2
    },
    {
      "userName": "om",
      "email": "om@gmail.com",
      "panNumber": "dfghj56567p",
      "mobileNumber": "56565656",
      "gender": "female",
      "password": "om$34",
      "id": 3
    }
  ],
  "user": [],
  "hotelDetails": [
    {
      "ownerName": "poonam",
      "mobileNumber": "9898989888",
      "hotelName": "Hotel Shivali",
      "hotelAdress": "Mumbai",
      "hotelNumber": "98989898",
      "hotelMenu": "nonveg",
      "rooms": "2",
      "pass": "poonam$34",
      "checkBox": "",
      "id": 1
    },
    {
      "ownerName": "poonam",
      "mobileNumber": "9898989888",
      "hotelName": "Hotel Taj",
      "hotelAdress": "Mumbai",
      "hotelNumber": "98989898",
      "hotelMenu": "nonveg",
      "rooms": "2",
      "pass": "poonam$34",
      "checkBox": "",
      "id": 2
    },
    {
      "ownerName": "poonam",
      "mobileNumber": "9898989888",
      "hotelName": "Hotel Sonpari",
      "hotelAdress": "Mumbai",
      "hotelNumber": "5555555",
      "hotelMenu": "nonveg",
      "rooms": "7",
      "pass": "poonam$34",
      "checkBox": "",
      "id": 3
    },
    {
      "ownerName": "pooja",
      "mobileNumber": "9898989888",
      "hotelName": "Hotel Sonpari",
      "hotelAdress": "Mumbai",
      "hotelNumber": "98989898",
      "hotelMenu": "nonveg",
      "rooms": "7",
      "pass": "poonam$34",
      "checkBox": "",
      "id": 4
    },
    {
      "ownerName": "ddddd",
      "mobileNumber": "333333",
      "hotelName": "eeeeeeeee",
      "hotelAdress": "333",
      "hotelNumber": "3333333",
      "hotelMenu": "",
      "rooms": "6",
      "pass": "deS434",
      "checkBox": "",
      "id": 5
    },
    {
      "ownerName": "ddddd",
      "mobileNumber": "333333",
      "hotelName": "eeeeeeeee",
      "hotelAdress": "333",
      "hotelNumber": "3333333",
      "hotelMenu": "DDD",
      "rooms": "6",
      "pass": "JJJJJJMJJJ",
      "checkBox": "",
      "id": 6
    },
    {
      "ownerName": "poonam",
      "mobileNumber": "33333",
      "hotelName": "taj",
      "hotelAdress": "sss",
      "hotelNumber": "333333333",
      "hotelMenu": "dddd",
      "rooms": "2",
      "pass": "dddddddddd",
      "checkBox": null,
      "id": 7
    },
    {
      "ownerName": "poja",
      "mobileNumber": "44444444444",
      "hotelName": "4ggg",
      "hotelAdress": "ggg",
      "hotelNumber": "8888",
      "hotelMenu": "g",
      "rooms": "3",
      "pass": "pppppppppppp",
      "checkBox": "",
      "id": 8
    },
    {
      "ownerName": "",
      "mobileNumber": "",
      "hotelName": "",
      "hotelAdress": "",
      "hotelNumber": "",
      "hotelMenu": "",
      "rooms": "",
      "pass": "",
      "checkBox": "",
      "id": 9
    },
    {
      "ownerName": "",
      "mobileNumber": "",
      "hotelName": "",
      "hotelAdress": "",
      "hotelNumber": "",
      "hotelMenu": "",
      "rooms": "",
      "pass": "",
      "checkBox": "",
      "id": 10
    },
    {
      "ownerName": "",
      "mobileNumber": "",
      "hotelName": "",
      "hotelAdress": "",
      "hotelNumber": "",
      "hotelMenu": "",
      "rooms": "",
      "pass": "",
      "checkBox": "",
      "id": 11
    },
    {
      "ownerName": "",
      "mobileNumber": "",
      "hotelName": "",
      "hotelAdress": "",
      "hotelNumber": "",
      "hotelMenu": "",
      "rooms": "",
      "pass": "",
      "checkBox": "",
      "id": 12
    },
    {
      "ownerName": "",
      "mobileNumber": "",
      "hotelName": "",
      "hotelAdress": "",
      "hotelNumber": "",
      "hotelMenu": "",
      "rooms": "",
      "pass": "",
      "checkBox": "",
      "id": 13
    },
    {
      "ownerName": null,
      "mobileNumber": null,
      "hotelName": null,
      "hotelAdress": null,
      "hotelNumber": null,
      "hotelMenu": null,
      "rooms": null,
      "pass": null,
      "checkBox": null,
      "id": 14
    },
    {
      "ownerName": "",
      "mobileNumber": "",
      "hotelName": "",
      "hotelAdress": "",
      "hotelNumber": "",
      "hotelMenu": "",
      "rooms": "",
      "pass": "",
      "checkBox": "",
      "id": 15
    },
    {
      "ownerName": "",
      "mobileNumber": "",
      "hotelName": "",
      "hotelAdress": "",
      "hotelNumber": "",
      "hotelMenu": "",
      "rooms": "",
      "pass": "",
      "checkBox": "",
      "id": 16
    },
    {
      "ownerName": "",
      "mobileNumber": "",
      "hotelName": "",
      "hotelAdress": "",
      "hotelNumber": "",
      "hotelMenu": "",
      "rooms": "",
      "pass": "",
      "checkBox": "",
      "id": 17
    },
    {
      "ownerName": "",
      "mobileNumber": "",
      "hotelName": "",
      "hotelAdress": "",
      "hotelNumber": "",
      "hotelMenu": "",
      "rooms": "",
      "pass": "",
      "checkBox": "",
      "id": 18
    },
    {
      "ownerName": "",
      "mobileNumber": "",
      "hotelName": "",
      "hotelAdress": "",
      "hotelNumber": "",
      "hotelMenu": "",
      "rooms": "",
      "pass": "",
      "checkBox": "",
      "id": 19
    },
    {
      "ownerName": null,
      "mobileNumber": null,
      "hotelName": null,
      "hotelAdress": null,
      "hotelNumber": null,
      "hotelMenu": null,
      "rooms": null,
      "pass": null,
      "checkBox": null,
      "id": 20
    },
    {
      "ownerName": "",
      "mobileNumber": "",
      "hotelName": "",
      "hotelAdress": "",
      "hotelNumber": "",
      "hotelMenu": "",
      "rooms": "",
      "pass": "",
      "checkBox": "",
      "id": 21
    },
    {
      "ownerName": "",
      "mobileNumber": "",
      "hotelName": "",
      "hotelAdress": "",
      "hotelNumber": "",
      "hotelMenu": "",
      "rooms": "",
      "pass": "",
      "checkBox": "",
      "id": 22
    }
  ],
  "hotelBooking": []
}